pycache/__init__.py
pycache/_cache/__init__.py
pycache/_cache/_cache.py
pycache/_cache/_memmory_db.py
pycache/_cache/_timer.py
pycache/_scheduler/_scheduler.py
pycache/_shared/_parser.py
pycache/_shared/_singleton.py
py_cache-0.3.2.dist-info/WHEEL
py_cache-0.3.2.dist-info/METADATA
py_cache-0.3.2.dist-info/RECORD
