Metadata-Version: 2.1
Name: py-cache
Version: 0.3.2
Summary: Simple to use caching decorator with more capabilites than the default one.
Home-page: https://github.com/HuiiBuh/pycache
License: MIT
Keywords: cache,schedule,method,function,asyncio
Author: HuiiBuh
Maintainer: HuiiBuh
Requires-Python: >=3.6,<4.0
Classifier: License :: OSI Approved :: MIT License
Classifier: Programming Language :: Python :: 3
Classifier: Programming Language :: Python :: 3.6
Classifier: Programming Language :: Python :: 3.7
Classifier: Programming Language :: Python :: 3.8
Project-URL: Repository, https://github.com/HuiiBuh/pycache
